Metadata-Version: 2.1
Name: ICQ-client
Version: 0.1.1
Summary: ICQ_client
Home-page: UNKNOWN
Author: Evseev Yurii
Author-email: mousedrw@ya.ru
License: UNKNOWN
Platform: UNKNOWN
Requires-Dist: PyQt5
Requires-Dist: sqlalchemy
Requires-Dist: pycryptodome
Requires-Dist: pycryptodomex
